mcp_remote_control/__init__.py
mcp_remote_control/main.py
mcp_remote_control/roku_bridge.py
mcp_remote_control/server.py
mcp_remote_control-0.1.0.dist-info/METADATA
mcp_remote_control-0.1.0.dist-info/WHEEL
mcp_remote_control-0.1.0.dist-info/entry_points.txt
mcp_remote_control-0.1.0.dist-info/top_level.txt
mcp_remote_control-0.1.0.dist-info/RECORD
