Metadata-Version: 2.4
Name: mcp-remote-control
Version: 0.1.0
Summary: AI-powered local network control for TVs and devices. Currently supports Roku TVs via ECP.
Requires-Python: >=3.12
Requires-Dist: httpx>=0.28.1
Requires-Dist: mcp[cli]>=1.23.3
